divintseg/__init__.py
divintseg/_core.py
divintseg-0.7.0.dist-info/LICENSE.md
divintseg-0.7.0.dist-info/METADATA
divintseg-0.7.0.dist-info/WHEEL
divintseg-0.7.0.dist-info/RECORD
