Metadata-Version: 2.1
Name: divintseg
Version: 0.7.0
Summary: Tools for computing diversity, integration and segregation metrics
Home-page: https://github.com/vengroff/divintseg
License: HL3-CL-ECO-EXTR-FFD-LAW-MIL-SV
Keywords: diversity,integration,segregation,demographics
Author: Darren Vengroff
Requires-Python: >=3.9,<4.0
Classifier: Development Status :: 3 - Alpha
Classifier: Intended Audience :: Science/Research
Classifier: License :: Other/Proprietary License
Classifier: Programming Language :: Python :: 3
Classifier: Programming Language :: Python :: 3.9
Classifier: Programming Language :: Python :: 3.10
Classifier: Programming Language :: Python :: 3.11
Provides-Extra: docs
Requires-Dist: genbadge[all] (>=1.1.1,<2.0.0)
Requires-Dist: nbsphinx (>=0.9.3,<0.10.0)
Requires-Dist: numpy (>=2.0.0,<3.0.0)
Requires-Dist: pandas (>=2.1.3,<3.0.0)
Requires-Dist: sphinx-copybutton (>=0.5.1,<0.6.0) ; extra == "docs"
Requires-Dist: sphinx-rtd-theme (==2.0.0) ; extra == "docs"
Requires-Dist: sphinxcontrib-napoleon (==0.7) ; extra == "docs"
Requires-Dist: toml (>=0.10.0,<0.11.0) ; extra == "docs"
Project-URL: Repository, https://github.com/vengroff/divintseg
